mypackage/__init__.py
mypackage/draw.py
mypackage_2020-1.0.0.dist-info/LICENSE
mypackage_2020-1.0.0.dist-info/METADATA
mypackage_2020-1.0.0.dist-info/WHEEL
mypackage_2020-1.0.0.dist-info/top_level.txt
mypackage_2020-1.0.0.dist-info/RECORD
